numerical/__init__.py
numerical/derivative.py
numerical/interpolation.py
numerical/area/__init__.py
numerical/area/grid.py
numerical/integration/__init__.py
numerical/integration/gauss.py
numerical/splines/__init__.py
numerical/splines/definitions.py
numerical/splines/derivatives.py
numerical/utils/__init__.py
numerical/utils/integration.py
numerical/utils/interpolation.py
numerical/utils/linalg.py
tests/__init__.py
tests/test_grid.py
tests/test_integration_gauss.py
tests/test_interpolation.py
tests/test_splines.py
scikit_numerical-0.1.1.dist-info/LICENCE
scikit_numerical-0.1.1.dist-info/METADATA
scikit_numerical-0.1.1.dist-info/WHEEL
scikit_numerical-0.1.1.dist-info/top_level.txt
scikit_numerical-0.1.1.dist-info/RECORD
