Metadata-Version: 2.1
Name: scikit-numerical
Version: 0.1.1
Summary: Tools for numerical math calculations
Home-page: https://github.com/Bellator95/scikit-numerical
Author: Maksym Shpakovych
Author-email: maksym.shpakovych@gmail.com
License: UNKNOWN
Platform: UNKNOWN
Classifier: Programming Language :: Python :: 3
Classifier: License :: OSI Approved :: MIT License
Classifier: Operating System :: OS Independent
